changelog/__init__.py
changelog/_version.py
changelog/commands.py
changelog/exceptions.py
changelog/templates.py
changelog/utils.py
changelog_cli-0.7.1.dist-info/METADATA
changelog_cli-0.7.1.dist-info/WHEEL
changelog_cli-0.7.1.dist-info/entry_points.txt
changelog_cli-0.7.1.dist-info/top_level.txt
changelog_cli-0.7.1.dist-info/RECORD
