Metadata-Version: 2.1
Name: changelog-cli
Version: 0.7.1
Summary: Command line interface for managing CHANGELOG.md files
Home-page: https://github.com/mc706/changelog-cli
Author: Ryan McDevitt
Author-email: mcdevitt.ryan@gmail.com
License: UNKNOWN
Platform: UNKNOWN
Classifier: Development Status :: 4 - Beta
Classifier: Environment :: Console
Classifier: Intended Audience :: Developers
Classifier: Programming Language :: Python :: 2.7
Classifier: Programming Language :: Python :: 3
Classifier: Programming Language :: Python :: 3.4
Classifier: Programming Language :: Python :: 3.5
Classifier: Programming Language :: Python :: 3.6
Classifier: Programming Language :: Python :: 3.7
Classifier: Programming Language :: Python :: 3.8
Classifier: Topic :: Documentation
Classifier: Topic :: Software Development :: Build Tools
Classifier: Topic :: Software Development :: Documentation
Classifier: Topic :: Utilities
Requires-Dist: click
Provides-Extra: dev
Requires-Dist: prospector ; extra == 'dev'
Requires-Dist: twine ; extra == 'dev'
Requires-Dist: coverage ; extra == 'dev'
Requires-Dist: invoke ; extra == 'dev'
Requires-Dist: wheel ; extra == 'dev'
Requires-Dist: mock ; extra == 'dev'
